aiogemini/__init__.py
aiogemini/abstract.py
aiogemini/security.py
aiogemini/client/__init__.py
aiogemini/client/__main__.py
aiogemini/client/client.py
aiogemini/client/protocol.py
aiogemini/server/__init__.py
aiogemini/server/__main__.py
aiogemini/server/fileserver.py
aiogemini/server/protocol.py
aiogemini/server/server.py
aiogemini-0.2.0.dist-info/METADATA
aiogemini-0.2.0.dist-info/WHEEL
aiogemini-0.2.0.dist-info/top_level.txt
aiogemini-0.2.0.dist-info/RECORD
